kriss_matcher-0.0.1.dist-info/METADATA
kriss_matcher-0.0.1.dist-info/WHEEL
kriss_matcher-0.0.1.dist-info/licenses/LICENSE
kriss_matcher.libs/libquadmath-96973f99.so.0
kriss_matcher.libs/libgfortran-040039e1.so.5
kriss_matcher/__init__.py
kriss_matcher/__init__.pyi
kriss_matcher/py.typed
kriss_matcher/kriss_matcher.pypy310-pp73-x86_64-linux-gnu.so
kriss_matcher-0.0.1.dist-info/RECORD
