Metadata-Version: 2.3
Name: kriss_matcher
Version: 0.0.1
Classifier: Programming Language :: Rust
Classifier: Programming Language :: Python :: Implementation :: CPython
Classifier: Programming Language :: Python :: Implementation :: PyPy
Requires-Dist: numpy >=1.26.4
Requires-Dist: pip
Requires-Dist: pytest ; extra == 'tests'
Requires-Dist: pytest-sugar ; extra == 'tests'
Provides-Extra: tests
License-File: LICENSE
Summary: Rust implementation of the paper 'KISS-Matcher: Fast and Robust Point Cloud Registration Revisited'
Home-Page: https://github.com/szobov/kriss_matcher
Author: Sergei Zobov <sergei@szobov.ru>
Author-email: Sergei Zobov <sergei@szobov.ru>
License: Apache-2.0
Requires-Python: >=3.9
Project-URL: Source Code, https://github.com/szobov/kriss_matcher
